scrachy-0.20.0.dist-info/METADATA
scrachy-0.20.0.dist-info/WHEEL
scrachy-0.20.0.dist-info/entry_points.txt
scrachy-0.20.0.dist-info/licenses/LICENSE.md
scrachy/__init__.py
scrachy/addons.py
scrachy/cli/__init__.py
scrachy/cli/benchmark.py
scrachy/cli/webdriver_server.py
scrachy/content/__init__.py
scrachy/content/boilerpipe.py
scrachy/content/bs4.py
scrachy/db/__init__.py
scrachy/db/base.py
scrachy/db/engine.py
scrachy/db/models.py
scrachy/db/repositories.py
scrachy/exceptions.py
scrachy/http_.py
scrachy/middleware/__init__.py
scrachy/middleware/filter.py
scrachy/middleware/httpcache.py
scrachy/middleware/selenium.py
scrachy/settings/__init__.py
scrachy/settings/defaults/__init__.py
scrachy/settings/defaults/filter.py
scrachy/settings/defaults/fingerprinter.py
scrachy/settings/defaults/policy.py
scrachy/settings/defaults/selenium.py
scrachy/settings/defaults/storage.py
scrachy/settings/prefixed.py
scrachy/utils/__init__.py
scrachy/utils/datetime.py
scrachy/utils/db.py
scrachy/utils/hash.py
scrachy/utils/imports.py
scrachy/utils/numeric.py
scrachy/utils/request.py
scrachy/utils/selenium.py
scrachy/utils/settings.py
scrachy/utils/sqltypes.py
scrachy/utils/strings.py
scrachy-0.20.0.dist-info/RECORD
