Metadata-Version: 2.1
Name: scrachy
Version: 0.20.0
Summary: Provides an SqlAlchemy based cache storage backend, a Selenium middleware, and a few other utilities for working with Scrapy.
Keywords: httpcache,scraping,scrapy,selenium
Author-Email: Reid Swanson <reid@reidswanson.com>
License: # GNU LESSER GENERAL PUBLIC LICENSE
Project-URL: Homepage, https://bitbucket.org/reidswanson/scrachy
Project-URL: Documentation, https://scrachy.readthedocs.io/en/latest
Requires-Python: >=3.12
Requires-Dist: cron-converter>=1.2.1
Requires-Dist: msgspec>=0.19.0
Requires-Dist: psutil>=7.0.0
Requires-Dist: python-dotenv>=1.0.1
Requires-Dist: pyyaml>=6.0.2
Requires-Dist: scrapy>=2.12.0
Requires-Dist: selenium>=4.29.0
Requires-Dist: twisted>=24.11.0
Requires-Dist: w3lib>=2.3.1
Requires-Dist: pywin32; os_name == "nt"
Requires-Dist: sqlalchemy>=2.0.39
Requires-Dist: sqlalchemy-utils>=0.41.2
Requires-Dist: arrow>=1.3.0
Requires-Dist: psycopg>=3.2.6
Requires-Dist: scipy>=1.12.0
Requires-Dist: rwskit[all]>=0.24.0
Provides-Extra: all
Requires-Dist: scrachy[benchmark,content,html,mysql,postgresql]; extra == "all"
Provides-Extra: benchmark
Requires-Dist: tabulate>=0.9.0; extra == "benchmark"
Provides-Extra: content
Requires-Dist: beautifulsoup4>=4.13.3; extra == "content"
Requires-Dist: boilerpy3>=1.0.7; extra == "content"
Provides-Extra: html
Requires-Dist: html5lib>=1.1; extra == "html"
Requires-Dist: lxml>=5.3.1; extra == "html"
Provides-Extra: mysql
Requires-Dist: pymysql>=1.1.1; extra == "mysql"
Provides-Extra: postgresql
Requires-Dist: psycopg>=3.2.6; extra == "postgresql"
